zfnew
