Metadata-Version: 2.1
Name: zfnew
Version: 0.0.2
Summary: 新版正方教务管理系统API
Home-page: https://neroasmar.top/zfnew/
Author: NeroAsmar
Author-email: neroasmarr@gmail.com
License: UNKNOWN
Platform: UNKNOWN
Classifier: Intended Audience :: Developers
Classifier: License :: OSI Approved :: GNU General Public License v3 (GPLv3)
Classifier: Programming Language :: Python :: 3
Classifier: Programming Language :: Python :: 3.4
Classifier: Programming Language :: Python :: 3.5
Classifier: Programming Language :: Python :: 3.6
Requires-Python: >=3.0.0
